my_dash_mic_recorder_component/MyDashMicRecorderComponent.py
my_dash_mic_recorder_component/__init__.py
my_dash_mic_recorder_component/_imports_.py
my_dash_mic_recorder_component/async-MyDashMicRecorderComponent.js
my_dash_mic_recorder_component/async-MyDashMicRecorderComponent.js.map
my_dash_mic_recorder_component/metadata.json
my_dash_mic_recorder_component/my_dash_mic_recorder_component.min.js
my_dash_mic_recorder_component/my_dash_mic_recorder_component.min.js.map
my_dash_mic_recorder_component/package-info.json
my_dash_mic_recorder_component-0.0.1.dist-info/LICENSE
my_dash_mic_recorder_component-0.0.1.dist-info/METADATA
my_dash_mic_recorder_component-0.0.1.dist-info/WHEEL
my_dash_mic_recorder_component-0.0.1.dist-info/top_level.txt
my_dash_mic_recorder_component-0.0.1.dist-info/RECORD
