Metadata-Version: 2.1
Name: my-dash-mic-recorder-component
Version: 0.0.1
Summary: my dash mic recorder
Author: me <me@gmail.com>
License: MIT
Classifier: Framework :: Dash
License-File: LICENSE
